poethepoet_tasks/__init__.py
poethepoet_tasks/helpers/__init__.py
poethepoet_tasks/helpers/docstrings.py
poethepoet_tasks/helpers/inspection.py
poethepoet_tasks/resources/__init__.py
poethepoet_tasks/resources/ruff.toml
poethepoet_tasks/tags.py
poethepoet_tasks/task_collection.py
poethepoet_tasks/tasks.py
poethepoet_tasks-0.3.0.dist-info/WHEEL
poethepoet_tasks-0.3.0.dist-info/METADATA
poethepoet_tasks-0.3.0.dist-info/RECORD
