Metadata-Version: 2.4
Name: poethepoet-tasks
Version: 0.3.0
Summary: A tasks package with common project tasks for Poe the Poet.
Keywords: automation,tasks,task-runner,poetry,poe,poethepoet
Author: Nat Noordanus
Author-email: Nat Noordanus <n@noordan.us>
License-Expression: MIT
Classifier: Topic :: Software Development :: Build Tools
Requires-Dist: black>=25.1.0
Requires-Dist: mypy>=1.16.0
Requires-Dist: poethepoet>=0.34.0
Requires-Dist: pytest>=8.3.5
Requires-Dist: ruff>=0.11.12
Requires-Python: >=3.10
Project-URL: homepage, https://github.com/nat-n/poethepoet-tasks
Project-URL: repository, https://github.com/nat-n/poethepoet-tasks
